MANIFEST.in
README.rst
setup.cfg
setup.py
hpd20/README.rst
hpd20/__init__.py
hpd20/__init__.pyc
hpd20/chain.py
hpd20/chain.pyc
hpd20/ethnic_scales.py
hpd20/ethnic_scales.pyc
hpd20/hpd20.py
hpd20/hpd20.pyc
hpd20/hpd20wx.py
hpd20/hpd20wx.pyc
hpd20/instrumentname.py
hpd20/instrumentname.pyc
hpd20/kit.py
hpd20/kit.pyc
hpd20/melodypadpattern.py
hpd20/melodypadpattern.pyc
hpd20/memoryops.py
hpd20/memoryops.pyc
hpd20/memoryops_unittests.py
hpd20/pad.py
hpd20/pad.pyc
hpd20/ratios.py
hpd20/read_scl.py
hpd20/scaledialog.py
hpd20/scaledialog.pyc
hpd20/scales.py
hpd20/scales.pyc
hpd20/scales_unittests.py
hpd20.egg-info/PKG-INFO
hpd20.egg-info/SOURCES.txt
hpd20.egg-info/dependency_links.txt
hpd20.egg-info/entry_points.txt
hpd20.egg-info/requires.txt
hpd20.egg-info/top_level.txt