Metadata-Version: 1.1
Name: hpd20
Version: 0.0.9
Summary: hpd-20 simple patch editor and librarian
Home-page: http://github.com/scjurgen/hpd-20
Author: Jürgen Schwietering
Author-email: scjurgen@yahoo.com
License: MIT
Keywords: roland,handsonic,hpd20,hpd-20,percussion,editor,librarian,kit,pad
Platform: UNKNOWN
Classifier: Development Status :: 3 - Alpha
Classifier: Environment :: Other Environment
Classifier: Intended Audience :: End Users/Desktop
Classifier: Topic :: Software Development :: Build Tools
Classifier: Topic :: Multimedia :: Sound/Audio :: Editors
Classifier: License :: OSI Approved :: GNU General Public License (GPL)
Classifier: Programming Language :: Python :: 2.7
